LICENSE
MANIFEST.in
README.md
changelog
setup.py
batch_run_cmd/__init__.py
batch_run_cmd/batch_run_cmd.py
batch_run_cmd.egg-info/PKG-INFO
batch_run_cmd.egg-info/SOURCES.txt
batch_run_cmd.egg-info/dependency_links.txt
batch_run_cmd.egg-info/entry_points.txt
batch_run_cmd.egg-info/top_level.txt